ggui/__init__.py
ggui/clickables.py
ggui/container.py
ggui/progress_bar.py
ggui/style.py
ggui/text.py
ggui/widget.py
gl_ggui-0.0.3.dist-info/LICENSE
gl_ggui-0.0.3.dist-info/METADATA
gl_ggui-0.0.3.dist-info/WHEEL
gl_ggui-0.0.3.dist-info/top_level.txt
gl_ggui-0.0.3.dist-info/RECORD
