Metadata-Version: 2.1
Name: gl-ggui
Version: 0.0.3
Summary: Package providing simple GUI features on pygame and pyOpenGl
Home-page: https://github.com/arthur-hav/GGUI
Author: Arthur Havlicek
Author-email: arthurhavlicek@gmail.com
License: UNKNOWN
Platform: UNKNOWN
Classifier: Programming Language :: Python :: 3
Classifier: License :: OSI Approved :: MIT License
Classifier: Operating System :: OS Independent
Requires-Python: >=3.6
